loglikelihood_estimator/__init__.py
loglikelihood_estimator/sfa.py
loglikelihood_estimator-0.1.dist-info/METADATA
loglikelihood_estimator-0.1.dist-info/WHEEL
loglikelihood_estimator-0.1.dist-info/top_level.txt
loglikelihood_estimator-0.1.dist-info/RECORD
