Metadata-Version: 2.1
Name: loglikelihood-estimator
Version: 0.1
Requires-Dist: numpy
Requires-Dist: pandas
Requires-Dist: scipy
